Partie_Verilog/Multiplier_16bit/multi8bit.v
module multi8bit(a, b, sum);
    input [7:0] a;
    input [7:0] b;
    output [15:0] sum;

assign sum = a * b;

endmodule

Partie_Verilog/Multiplier_16bit/test_multi8bit.v
`timescale 1ns / 1ps
`include "multi8bit.v"

module stimulus;
  // Inputs
  reg [7:0] a;
  reg [7:0] b;
  // Outputs
  wire [15:0] sum;
  // Instantiate the Unit Under Test (UUT)
  multi8bit uut (
    .a(a),
    .b(b),
    .sum(sum)
  );

  initial begin
    $dumpfile("multi8bit.vcd");
    $dumpvars(0, stimulus);
    // Initialize Inputs
    a = 8'b00000000;
    b = 8'b00000000;

    #20 a = 8'b00000001;
    #20 b = 8'b00000011;

    #20 b = 8'b00000011;
    #20 a = 8'b00000111;
    
    #20 a = 8'b10000111;
    #20 b = 8'b00001111;

    #20 a = 8'b10000000;
    #20 b = 8'b00010101;
    #40;
  end  

  initial begin
    $monitor("t=%3d a=%b,b=%b,sum=%b\n", $time, a, b, sum);
  end
endmodule

Partie_Verilog/Multiplier_16bit/multi8bit.vcd
$date
	Fri Mar 10 18:16:38 2023
$end
$version
	Icarus Verilog
$end
$timescale
	1ps
$end
$scope module stimulus $end
$var wire 16 ! sum [15:0] $end
$var reg 8 " a [7:0] $end
$var reg 8 # b [7:0] $end
$scope module uut $end
$var wire 8 $ a [7:0] $end
$var wire 8 % b [7:0] $end
$var wire 16 & sum [15:0] $end
$upscope $end
$upscope $end
$enddefinitions $end
$comment Show the parameter values. $end
$dumpall
$end
#0
$dumpvars
b0 &
b0 %
b0 $
b0 #
b0 "
b0 !
$end
#20000
b1 "
b1 $
#40000
b11 !
b11 &
b11 #
b11 %
#80000
b10101 !
b10101 &
b111 "
b111 $
#100000
b110010101 !
b110010101 &
b10000111 "
b10000111 $
#120000
b11111101001 !
b11111101001 &
b1111 #
b1111 %
#140000
b11110000000 !
b11110000000 &
b10000000 "
b10000000 $
#160000
b101010000000 !
b101010000000 &
b10101 #
b10101 %
